<BackupInst xmlns="http://www.microsoft.com/GroupPolicy/GPOOperations/Manifest"><GPOGuid><![CDATA[{FF7E94E3-0C87-459A-9661-9E1E0AADE3C7}]]></GPOGuid><GPODomain><![CDATA[ansible.local]]></GPODomain><GPODomainGuid><![CDATA[{470e3bdc-8d5c-47c8-a1f9-855b54c36d9f}]]></GPODomainGuid><GPODomainController><![CDATA[myVM-00.ansible.local]]></GPODomainController><BackupTime><![CDATA[2019-06-14T11:10:59]]></BackupTime><ID><![CDATA[{658FD395-BACC-43FB-95BA-5B6A381FEC4E}]]></ID><Comment><![CDATA[]]></Comment><GPODisplayName><![CDATA[salesPolicy]]></GPODisplayName></BackupInst>
